todo_tui/__init__.py
todo_tui/app.py
todo_tui/cloud_sync.py
todo_tui/encryption.py
todo_tui/icons.py
todo_tui/markdown_syntax.py
todo_tui/models.py
todo_tui/storage.py
todo_tui/theme.css
todo_tui/themes.py
todo_tui/demo_data/demo-personal-001.json
todo_tui/demo_data/demo-side-003.json
todo_tui/demo_data/demo-work-002.json
todo_tui/demo_data/notes.json
todo_tui/demo_data/projects.json
todo_tui/demo_data/settings.json
todo_tui/demo_data/snippets.json
todo_tui/widgets/__init__.py
todo_tui/widgets/clock_widget.py
todo_tui/widgets/dashboard.py
todo_tui/widgets/dialogs.py
todo_tui/widgets/forecast_widget.py
todo_tui/widgets/pomodoro_widget.py
todo_tui/widgets/productivity_tabs.py
todo_tui/widgets/project_list.py
todo_tui/widgets/quotes_card.py
todo_tui/widgets/scratchpad.py
todo_tui/widgets/snippets.py
todo_tui/widgets/task_detail.py
todo_tui/widgets/task_list.py
todo_tui/widgets/weather_widget.py
tuido_tui-0.3.1.dist-info/METADATA
tuido_tui-0.3.1.dist-info/WHEEL
tuido_tui-0.3.1.dist-info/entry_points.txt
tuido_tui-0.3.1.dist-info/top_level.txt
tuido_tui-0.3.1.dist-info/RECORD
