Metadata-Version: 2.4
Name: tuido-tui
Version: 0.3.1
Summary: A beautiful Terminal User Interface (TUI) todo application built with Textual, featuring multiple themes, Pomodoro timer, and markdown notes
Author-email: Dave Mostoller <dmostoller@gmail.com>
License: MIT
Project-URL: Homepage, https://tuido.dev
Project-URL: Documentation, https://tuido.dev
Project-URL: Repository, https://github.com/dmostoller/tuido
Project-URL: Bug Tracker, https://github.com/dmostoller/tuido/issues
Keywords: todo,tui,terminal,textual,productivity,task-manager,pomodoro,cli
Classifier: Development Status :: 4 - Beta
Classifier: Environment :: Console
Classifier: Intended Audience :: Developers
Classifier: Intended Audience :: End Users/Desktop
Classifier: License :: OSI Approved :: MIT License
Classifier: Operating System :: OS Independent
Classifier: Programming Language :: Python :: 3
Classifier: Programming Language :: Python :: 3.12
Classifier: Programming Language :: Python :: 3.13
Classifier: Topic :: Utilities
Classifier: Typing :: Typed
Requires-Python: >=3.12
Requires-Dist: cryptography>=41.0.0
Requires-Dist: httpx>=0.27.0
Requires-Dist: platformdirs>=4.0.0
Requires-Dist: plotext>=5.3.2
Requires-Dist: pyperclip>=1.8.0
Requires-Dist: python-dotenv>=1.0.0
Requires-Dist: requests>=2.31.0
Requires-Dist: textual[syntax]>=0.73.0
Requires-Dist: textual-dev>=1.6.1
Requires-Dist: tree-sitter>=0.25.0
Requires-Dist: tree-sitter-markdown>=0.3.0
